juju_act.py
juju_act-1.0.1.dist-info/DESCRIPTION.rst
juju_act-1.0.1.dist-info/METADATA
juju_act-1.0.1.dist-info/RECORD
juju_act-1.0.1.dist-info/WHEEL
juju_act-1.0.1.dist-info/entry_points.txt
juju_act-1.0.1.dist-info/metadata.json
juju_act-1.0.1.dist-info/top_level.txt
