Metadata-Version: 2.0
Name: juju-act
Version: 1.0.1
Summary: Juju plugin to improve the command line UI of Juju actions
Home-page: https://launchpad.net/juju-act
Author: Stuart Bishop
Author-email: stuart.bishop@canonical.com
License: GPLv3
Keywords: juju
Platform: UNKNOWN
Classifier: Development Status :: 5 - Production/Stable
Classifier: Environment :: Plugins
Classifier: Intended Audience :: Developers
Classifier: Intended Audience :: System Administrators
Classifier: License :: OSI Approved :: GNU General Public License v3 (GPLv3)
Classifier: Operating System :: OS Independent
Classifier: Topic :: System :: Installation/Setup
Classifier: Topic :: Utilities
Classifier: Programming Language :: Python :: 3
Requires-Dist: PyYAML
